[   
    {
      "title": "Portfolio",
      "imageSrc": "projects/portfolio.png",
      "description": "This project showcases my professional experiences, array of projects, skills and so on.",
      "skills": ["JavaScript","React", "HTML", "CSS"],
      "demo": "https://resha-portfolio.vercel.app/",
      "source": "https://github.com/re-sha/portfolio"
    },
    {
      "title": "Qatar Airlines",
      "imageSrc": "projects/airlines.png",
      "description": "Built an interactive flight booking site with dynamic data, modals, validation, and event handling.",
      "skills": ["JavaScript", "HTML", "CSS"],
      "demo": "https://re-sha.github.io/airlines-reservation/",
      "source": "https://github.com/re-sha/airlines-reservation"
    },
    {
      "title": "The Dental Studio",
      "imageSrc": "projects/dental-clinic.png",
      "description": "This project is a landing page for a dental clinic that illustrates services, reviews and so on.",
      "skills": ["HTML", "CSS", "minimalistic"],
      "demo": "https://re-sha.github.io/landing-page/",
      "source": "https://www.github.com"
    }
  ]